{"data": [{"party_code": "ano", "median": 73, "lo": 65, "hi": 81, "seats": 72, "difference": -6, "name": "ANO", "color": "#261060", "gain": "0.2756919977234034"}, {"party_code": "pirati", "median": 40, "lo": 35, "hi": 45, "seats": 41, "difference": 19, "name": "Piráti", "color": "#000000", "gain": "0.16696299604941447"}, {"party_code": "ods", "median": 25, "lo": 20, "hi": 31, "seats": 25, "difference": 0, "name": "ODS", "color": "#004494", "gain": "0.11612817754133256"}, {"party_code": "stan", "median": 19, "lo": 16, "hi": 24, "seats": 20, "difference": 14, "name": "STAN", "color": "#5d8c00", "gain": "0.09195086954827256"}, {"party_code": "spd", "median": 18, "lo": 13, "hi": 23, "seats": 17, "difference": -5, "name": "SPD", "color": "#ea2329", "gain": "0.0848083096058164"}, {"party_code": "cssd", "median": 12, "lo": 0, "hi": 15, "seats": 13, "difference": -2, "name": "ČSSD", "color": "#F07D00", "gain": "0.059982304051313245"}, {"party_code": "kscm", "median": 8, "lo": 0, "hi": 15, "seats": 7, "difference": -8, "name": "KSČM", "color": "#8c0000", "gain": "0.05525696763752372"}, {"party_code": "top-09", "median": 5, "lo": 0, "hi": 9, "seats": 5, "difference": -2, "name": "TOP 09", "color": "#723769", "gain": "0.052619944346226945"}, {"party_code": "kdu-csl", "median": 0, "lo": 0, "hi": 10, "seats": 0, "difference": -10, "name": "KDU-ČSL", "color": "#e6ac21", "gain": "0.04617821786254262"}], "date": "2020-12-14"}